WaveFunctionPropagation/1D potential along axis Z.png
WaveFunctionPropagation/1D potential along axis Z.svg
WaveFunctionPropagation/Help_function_library_yair.py
WaveFunctionPropagation/Locpot_class.py
WaveFunctionPropagation/Main_execution.pdf
WaveFunctionPropagation/Main_execution.py
WaveFunctionPropagation/Stage_1.py
WaveFunctionPropagation/Stage_2.py
WaveFunctionPropagation/Structure_vis.py
WaveFunctionPropagation/__init__.py
WaveFunctionPropagation/__main__.py
WaveFunctionPropagation/savitzky_golay.py
Yair_code/Help_function_library_yair.py
Yair_code/Locpot_class.py
Yair_code/Main_File.py
Yair_code/Main_execution.py
Yair_code/Stage_1.py
Yair_code/Stage_2.py
Yair_code/Structure_vis.py
Yair_code/__init__.py
Yair_code/__main__.py
Yair_code/savitzky_golay.py
WF_Prop-0.0.6.dist-info/METADATA
WF_Prop-0.0.6.dist-info/WHEEL
WF_Prop-0.0.6.dist-info/top_level.txt
WF_Prop-0.0.6.dist-info/RECORD
