Metadata-Version: 2.1
Name: WF-Prop
Version: 0.0.6
Summary: A python package for one-elecron wavefunction propagation
Home-page: https://github.com/Yairpt/Wave_Function_Propagation
Author: ['Yair Reichman', 'Maytal Caspary Toroker']
Author-email: yairpt@gmail.com
License: UNKNOWN
Keywords: charge transport,charge transfer,split step,wavefucntion time evolution,
Platform: UNKNOWN
Classifier: Development Status :: 3 - Alpha
Classifier: Intended Audience :: Developers
Classifier: Intended Audience :: Science/Research
Classifier: Natural Language :: English
Classifier: Topic :: Database
Classifier: Topic :: Education
Classifier: Topic :: Office/Business
Requires-Dist: pymatgen
Requires-Dist: pysimplegui
Requires-Dist: scipy
Requires-Dist: sympy
